[
    {
        "consultationId": 2207093,
        "title": "Ortho Clinical Diagnostics' Clinical Lab Products",
        "titleLocalized": "Ortho Clinical Diagnostics的临床实验室产品",
        "titleLocalizedCulture": "zh",
        "consultationParticipantId": 19303839,
        "consultationParticipantStatusId": 17,
        "providerName": "plivo",
        "clientId": 85,
        "clientName": "Fidelity Investments",
        "callType": "glg-conference",
        "scheduledDate": "2017-06-11T00:44:25.203Z",
        "lastUpdateDate": "2016-05-27T15:41:36.700Z",
        "status": "completed",
        "billableTimeRecorded": 0,
        "productTypeCategoryId": 1,
        "record": true,
        "transcribe": 0,
        "blockedByCompliance": false,
        "conferenceCallRequired": false,
        "auditorRequired": false,
        "client": {
            "id": 85,
            "name": "Fidelity Investments",
            "typeId": 2,
            "useGo": true,
            "isPSF": false
        },
        "blinding": {
            "hideClient": false,
            "hideCM": false,
            "councilMemberMaskingLabel": null
        },
        "councilMember": {
            "personId": 25037,
            "firstName": "Leonard",
            "lastName": "Levin",
            "email": "llevin@hotmail.com",
            "preferredCulture": "en-US",
            "councilMemberId": 48795,
            "bio": "Leonard Levin, MS, MBA, is the Administrative Laboratory Director at Holy Redeemer Hospital in Meadowbrook, PA. He has over 30 years of work experience in various capacities related to clinical laboratory sciences, including laboratory testing in clinical microbiology and serology, scientific writing of articles focusing on diagnosis, treatment, and epidemiology of HIV and AIDS, and management of clinical laboratories for urban as well as suburban hospitals.  Currently, in addition to hospital laboratory management, Len serves as a reviewer and writer of online continuing education modules for Gannett Healthcare. Len has been quoted in various clinical laboratory professional publications, including CAP Today, Laboratory Medicine, Advance for Medical Laboratory Professionals, and Medical Laboratory Observer (MLO).  He was also profiled recently in Ostomy Wound Management magazine, in which he highlighted the contributions of the clinical laboratory to the care of wound patients.",
            "hightlights": "Leonard has over 30 years of experience in the clinical lab (lab testing, clinical microbiology, serology, etc.). He let me know that, currently, his lab utilizes Ortho blood bank and gel technology products and that, in the past, when working at other hospitals, he utilized clinical chemistry analyzers \"for many years\" in addition to Ortho's blood bank products. Importantly, he noted the following regarding the Vitros system: \"I have directed laboratories utilizing Ortho Vitros 5600 chemistry/immunoassay analyzers. I am aware of the Vitros ECi immunodiagnostic system, the technology of which was incorporated into the immunoassay side of the Vitros 5600 system.\"",
            "headline": "Administrative Director, Laboratory Services at Holy Redeemer Health System (Pennsylvania, 2014-present)",
            "phone": null,
            "mobile": null,
            "phone2": null,
            "primaryPhoneType": "cell",
            "alternatePhone": "+818026799375",
            "smsDisabled": false,
            "countryName": "United States",
            "countryCode": "US",
            "companyId": 315705,
            "company": "HOLY REDEEMER HEALTH SYSTEM, INC.",
            "title": "Administrative Director, Laboratory Services",
            "hasCurrentTerms": 1,
            "termsLastSigned": "2016-11-09T06:26:15.280Z",
            "termsExpiredDate": "2017-11-09T06:26:15.280Z",
            "language": "en",
            "isCouncilMember": true,
            "primaryPhone": "+818026799375",
            "pinNumber": 222,
            "conferenceNumber": {
                "didNumberId": "A37701EC-F54B-E711-8145-0E573F34979E",
                "displayNumber": "+16467939347",
                "countryCode": "US",
                "displayTitle": "New York United States",
                "provider": "plivo",
                "providerPhoneId": "16467939347",
                "subProvider": null,
                "inboundPriority": 0,
                "outboundPriority": 0,
                "tollFree": false,
                "environment": "phadviger-devship",
                "providerPhoneLookup": "16467939347",
                "activeInd": true,
                "outboundCountries": [],
                "priority": 0,
                "formattedNumber": "+1 646-793-9347",
                "autoDialNumber": "+16467939347,,222#"
            },
            "dialOutConferenceNumber": {
                "didNumberId": "A37701EC-F54B-E711-8145-0E573F34979E",
                "displayNumber": "+16467939347",
                "countryCode": "US",
                "displayTitle": "New York United States",
                "provider": "plivo",
                "providerPhoneId": "16467939347",
                "subProvider": null,
                "inboundPriority": 0,
                "outboundPriority": 0,
                "tollFree": false,
                "environment": "phadviger-devship",
                "providerPhoneLookup": "16467939347",
                "activeInd": true,
                "outboundCountries": [],
                "priority": 0,
                "formattedNumber": "+1 646-793-9347"
            }
        },
        "primaryContact": {
            "personId": 853782,
            "firstName": "Dima",
            "lastName": "Mostovoy",
            "title": "Analyst",
            "email": "dima.mostovoy@fmr.com",
            "preferredCulture": null,
            "contactId": 289005,
            "phone": "+1 617-563-1370",
            "mobile": "",
            "countryName": "United States",
            "countryCode": "US",
            "isClientContact": true,
            "allowCallReminder": true,
            "showClientMessaging": true
        },
        "assistant": {
            "firstName": "Emily",
            "lastName": "Lyons",
            "email": "emily.lyons@fmr.com"
        },
        "schedulingContact": {
            "personId": 853782,
            "firstName": "Dima",
            "lastName": "Mostovoy",
            "title": "Analyst",
            "email": "dima.mostovoy@fmr.com",
            "preferredCulture": null,
            "contactId": 289005,
            "phone": "+1 617-563-1370",
            "mobile": "",
            "countryName": "United States",
            "countryCode": "US",
            "isClientContact": true,
            "allowCallReminder": true,
            "showClientMessaging": true,
            "pinNumber": 111,
            "conferenceNumber": {
                "didNumberId": "A37701EC-F54B-E711-8145-0E573F34979E",
                "displayNumber": "+16467939347",
                "countryCode": "US",
                "displayTitle": "New York United States",
                "provider": "plivo",
                "providerPhoneId": "16467939347",
                "subProvider": null,
                "inboundPriority": 0,
                "outboundPriority": 0,
                "tollFree": false,
                "environment": "phadviger-devship",
                "providerPhoneLookup": "16467939347",
                "activeInd": true,
                "outboundCountries": [],
                "priority": 0,
                "formattedNumber": "+1 646-793-9347",
                "autoDialNumber": "+16467939347,,111#"
            }
        },
        "primaryManager": {
            "personId": 1065874,
            "firstName": "Eric",
            "lastName": "Dimise Ph.D.",
            "title": "Senior Research Manager",
            "email": "edimise@glgroup.com",
            "loginName": "glgroup\\edimise",
            "phone": "+1 617 603-2349",
            "isEmployee": true
        },
        "delegate": {
            "personId": 1120434,
            "firstName": "Bhumit",
            "lastName": "Shah",
            "title": "Senior Associate",
            "email": "bshah@glgroup.com",
            "isEmployee": true
        },
        "scheduler": {
            "personId": null,
            "firstName": null,
            "lastName": null,
            "title": null,
            "email": null,
            "phone": null,
            "isEmployee": true
        },
        "dialinIsInactive": true,
        "pinNumbers": [
            {
                "pinType": "client",
                "pinNumber": 111,
                "consultationParticipantId": 19303839,
                "active": true
            },
            {
                "pinType": "councilMember",
                "pinNumber": 222,
                "consultationParticipantId": 19303839,
                "active": true
            },
            {
                "pinType": "auditor",
                "pinNumber": 333,
                "consultationParticipantId": 19303839,
                "active": true
            },
            {
                "pinType": "interpreter",
                "pinNumber": 444,
                "consultationParticipantId": 19303839,
                "active": true
            }
        ],
        "additionalDelegates": [
            {
                "id": 1015517,
                "firstname": "Karen",
                "lastname": "Wang",
                "email": "kwang2@glgroup.com",
                "consultationParticipantId": 19303839
            },
            {
                "id": 1050776,
                "firstname": "Betty",
                "lastname": "Gu",
                "email": "bgu@glgroup.com",
                "consultationParticipantId": 19303839
            }
        ],
        "msp": true,
        "defaultCallDuration": 60,
        "mspMarkup": false,
        "contractType": "CUSTOM OSP",
        "callLegs": [
            {
                "providerCallId": null,
                "direction": "out",
                "callerType": "councilMember",
                "pinNumber": 222,
                "provider": "plivo",
                "consultationParticipantId": 19303839,
                "origination": "client",
                "loginUtc": null,
                "joinConferenceUtc": null,
                "endUtc": "2017-06-11T02:00:38.000Z",
                "hangupCause": "Client is not on the call",
                "from": null,
                "to": null,
                "toCountry": null,
                "fromCountry": null,
                "startUtc": "2017-06-11T02:00:37.000Z",
                "active": false,
                "options": {
                    "record": true,
                    "auditorRequired": false
                }
            },
            {
                "providerCallId": "3abeda84-4e4d-11e7-a129-5b7ba22e31f2",
                "direction": "in",
                "callerType": "client",
                "pinNumber": 111,
                "provider": "plivo",
                "consultationParticipantId": 19303839,
                "origination": "sip",
                "loginUtc": "2017-06-11T02:25:34.000Z",
                "joinConferenceUtc": "2017-06-11T02:25:39.000Z",
                "endUtc": "2017-06-11T02:26:02.000Z",
                "hangupCause": null,
                "from": null,
                "to": null,
                "toCountry": null,
                "fromCountry": null,
                "startUtc": "2017-06-11T02:25:27.000Z",
                "active": false,
                "options": {
                    "record": true,
                    "auditorRequired": false
                }
            },
            {
                "providerCallId": "3cb839ef-7b95-4e1f-9bb0-2cd6506d3815",
                "direction": "out",
                "callerType": "councilMember",
                "pinNumber": 222,
                "provider": "plivo",
                "consultationParticipantId": 19303839,
                "origination": "client",
                "loginUtc": null,
                "joinConferenceUtc": null,
                "endUtc": "2017-06-12T03:51:02.000Z",
                "hangupCause": "NORMAL_CLEARING",
                "from": null,
                "to": null,
                "toCountry": null,
                "fromCountry": null,
                "startUtc": "2017-06-11T02:25:37.000Z",
                "active": false,
                "options": {
                    "record": true,
                    "auditorRequired": false
                }
            }
        ],
        "activeParticipantCount": 0,
        "billableTime": 0
    }
    ,{
        "consultationId": 2207093,
        "title": "Ortho Clinical Diagnostics' Clinical Lab Products",
        "titleLocalized": "Ortho Clinical Diagnostics的临床实验室产品",
        "titleLocalizedCulture": "zh",
        "consultationParticipantId": 19304286,
        "consultationParticipantStatusId": 10,
        "providerName": "twilio",
        "clientId": 85,
        "clientName": "Fidelity Investments",
        "callType": "glg-conference",
        "scheduledDate": "2016-06-21T14:00:00.000Z",
        "lastUpdateDate": "2016-06-21T10:15:11.186Z",
        "status": "processed",
        "billableTimeRecorded": 0,
        "productTypeCategoryId": 1,
        "record": true,
        "transcribe": 0,
        "blockedByCompliance": false,
        "conferenceCallRequired": false,
        "auditorRequired": false,
        "client": {
            "id": 85,
            "name": "Fidelity Investments",
            "typeId": 2,
            "useGo": true,
            "isPSF": false
        },
        "blinding": {
            "hideClient": false,
            "hideCM": false,
            "councilMemberMaskingLabel": null
        },
        "councilMember": {
            "personId": 939220,
            "firstName": "Weiwei",
            "lastName": "LIU",
            "email": "huashanvivian@126.com",
            "preferredCulture": "zh-s",
            "councilMemberId": 605736,
            "bio": "Weiwei LIU, PhD, is Deputy Director in the Clinical Diagnostic Lab at Shanghai Tenth People's Hospital, Affiliated to Tongji University and Associate Professor at Tongji University Medical College. Shanghai Tenth People's Hospital, founded in 1910, is a Class 3A hospital with medical treatment, teaching, research, prevention approved by Ministry of Health in 1993. Prior to that, from 2001 to June 2013, she was molecular testing group leader in Huashan Hospital. Huashan Hospital, founded in 1907, is under the Ministry of Health Hospital, Fudan University and the China Red Cross. Dr. Liu is good at molecular diagnostics, clinical standardization, viral testing and genetic testing. She has 12 years of experience in clinical laboratory testing",
            "hightlights": "Weiwei Liu, PhD, currently holds a leadership position in clinical diagnostics at the Tenth People's Hospital in Shanghai, with a focus on clinical diagnostics, standardization, and viral and genetic testing. She let us know that she currently utilizes the Vitros 5600 system and is familiar with market landscape of lab diagnostic products.",
            "headline": "Deputy Director, Clinical Diagnostic Lab, Shanghai Tenth People's Hospital and Associate Professor at Tongji University (2013-present)",
            "phone": "+8613162640870",
            "mobile": null,
            "phone2": null,
            "primaryPhoneType": "Office",
            "alternatePhone": null,
            "smsDisabled": false,
            "countryName": "China",
            "countryCode": "CN",
            "companyId": 3017159,
            "company": "Shanghai Tenth People's Hospital Affiliated to Tongji University",
            "title": "Deputy Director",
            "hasCurrentTerms": 1,
            "termsLastSigned": "2016-07-05T11:35:48.560Z",
            "termsExpiredDate": "2017-07-05T11:35:48.560Z",
            "language": "zh",
            "isCouncilMember": true,
            "primaryPhone": "+8613162640870",
            "pinNumber": 9368862,
            "conferenceNumber": {
                "didNumberId": "BC012291-424F-E711-8145-0E573F34979E",
                "displayNumber": "+19728517097",
                "countryCode": "US",
                "displayTitle": "United States",
                "provider": "twilio",
                "providerPhoneId": "PN1e399a9c223b5785ffe13f872f014274",
                "subProvider": null,
                "inboundPriority": 0,
                "outboundPriority": 0,
                "tollFree": false,
                "environment": "phadviger-devship",
                "providerPhoneLookup": "+19728517097",
                "activeInd": true,
                "outboundCountries": [],
                "priority": 0,
                "formattedNumber": "+1 972-851-7097",
                "autoDialNumber": "+19728517097,,9368862#"
            },
            "dialOutConferenceNumber": {
                "didNumberId": "BC012291-424F-E711-8145-0E573F34979E",
                "displayNumber": "+19728517097",
                "countryCode": "US",
                "displayTitle": "United States",
                "provider": "twilio",
                "providerPhoneId": "PN1e399a9c223b5785ffe13f872f014274",
                "subProvider": null,
                "inboundPriority": 0,
                "outboundPriority": 0,
                "tollFree": false,
                "environment": "phadviger-devship",
                "providerPhoneLookup": "+19728517097",
                "activeInd": true,
                "outboundCountries": [],
                "priority": 0,
                "formattedNumber": "+1 972-851-7097"
            }
        },
        "primaryContact": {
            "personId": 853782,
            "firstName": "Dima",
            "lastName": "Mostovoy",
            "title": "Analyst",
            "email": "dima.mostovoy@fmr.com",
            "preferredCulture": null,
            "contactId": 289005,
            "phone": "+1 617-563-1370",
            "mobile": "",
            "countryName": "United States",
            "countryCode": "US",
            "isClientContact": true,
            "allowCallReminder": true,
            "showClientMessaging": true
        },
        "assistant": {
            "firstName": "Emily",
            "lastName": "Lyons",
            "email": "emily.lyons@fmr.com"
        },
        "schedulingContact": {
            "personId": 853782,
            "firstName": "Dima",
            "lastName": "Mostovoy",
            "title": "Analyst",
            "email": "dima.mostovoy@fmr.com",
            "preferredCulture": null,
            "contactId": 289005,
            "phone": "+1 617-563-1370",
            "mobile": "",
            "countryName": "United States",
            "countryCode": "US",
            "isClientContact": true,
            "allowCallReminder": true,
            "showClientMessaging": true,
            "pinNumber": 4552513,
            "conferenceNumber": {
                "didNumberId": "BC012291-424F-E711-8145-0E573F34979E",
                "displayNumber": "+19728517097",
                "countryCode": "US",
                "displayTitle": "United States",
                "provider": "twilio",
                "providerPhoneId": "PN1e399a9c223b5785ffe13f872f014274",
                "subProvider": null,
                "inboundPriority": 0,
                "outboundPriority": 0,
                "tollFree": false,
                "environment": "phadviger-devship",
                "providerPhoneLookup": "+19728517097",
                "activeInd": true,
                "outboundCountries": [],
                "priority": 0,
                "formattedNumber": "+1 972-851-7097",
                "autoDialNumber": "+19728517097,,4552513#"
            }
        },
        "primaryManager": {
            "personId": 1065874,
            "firstName": "Eric",
            "lastName": "Dimise Ph.D.",
            "title": "Senior Research Manager",
            "email": "edimise@glgroup.com",
            "loginName": "glgroup\\edimise",
            "phone": "+1 617 603-2349",
            "isEmployee": true
        },
        "delegate": {
            "personId": 1120434,
            "firstName": "Bhumit",
            "lastName": "Shah",
            "title": "Senior Associate",
            "email": "bshah@glgroup.com",
            "isEmployee": true
        },
        "scheduler": {
            "personId": null,
            "firstName": null,
            "lastName": null,
            "title": null,
            "email": null,
            "phone": null,
            "isEmployee": true
        },
        "dialinIsInactive": true,
        "pinNumbers": [
            {
                "pinType": "councilMember",
                "pinNumber": 9368862,
                "consultationParticipantId": 19304286,
                "active": true
            },
            {
                "pinType": "client",
                "pinNumber": 4552513,
                "consultationParticipantId": 19304286,
                "active": true
            }
        ],
        "additionalDelegates": [
            {
                "id": 1015517,
                "firstname": "Karen",
                "lastname": "Wang",
                "email": "kwang2@glgroup.com",
                "consultationParticipantId": 19304286
            },
            {
                "id": 1050776,
                "firstname": "Betty",
                "lastname": "Gu",
                "email": "bgu@glgroup.com",
                "consultationParticipantId": 19304286
            }
        ],
        "msp": true,
        "defaultCallDuration": 60,
        "mspMarkup": false,
        "contractType": "CUSTOM OSP",
        "callLegs": [],
        "activeParticipantCount": 0,
        "billableTime": 0
    },
    {
        "consultationId": 2207093,
        "title": "Ortho Clinical Diagnostics' Clinical Lab Products",
        "titleLocalized": "Ortho Clinical Diagnostics的临床实验室产品",
        "titleLocalizedCulture": "zh",
        "consultationParticipantId": 19303898,
        "consultationParticipantStatusId": 5,
        "providerName": "twilio",
        "clientId": 85,
        "clientName": "Fidelity Investments",
        "callType": null,
        "scheduledDate": null,
        "lastUpdateDate": "2016-07-05T15:10:47.200Z",
        "status": null,
        "billableTimeRecorded": 0,
        "productTypeCategoryId": 1,
        "record": true,
        "transcribe": 0,
        "blockedByCompliance": false,
        "conferenceCallRequired": false,
        "auditorRequired": false,
        "client": {
            "id": 85,
            "name": "Fidelity Investments",
            "typeId": 2,
            "useGo": true,
            "isPSF": false
        },
        "blinding": {
            "hideClient": false,
            "hideCM": false,
            "councilMemberMaskingLabel": null
        },
        "councilMember": {
            "personId": 696309,
            "firstName": "Tina",
            "lastName": "FitzGerald",
            "email": "TFitzGerald30@comcast.net",
            "preferredCulture": "en",
            "councilMemberId": 481574,
            "bio": "Tina FitzGerald, MHA, MS, MLS (ASCP)cm, CPC is the Director of Laboratory Services at Anna Jaques Hospital, Newburyport MA,  a position she has held since May 2015. Ms. FitzGerald oversees the daily operations of the laboratory while ensuring departmental compliance with all regulatory agencies, personnel management, growth through relationship building, marketing and sales, selection, evaluation and implementation of laboratory instruments, and quality improvement and IT initiatives. Previously, Ms. FitzGerald was Lab Operations Manager for Holy Family Hospital at Merrimack Valley and Methuen and Laboratory Administrative Director for Merrimack Valley Hospital. As past Director of Physician Relations & Services at Women & Infants Hospital of Rhode Island,  Ms. FitzGerald oversaw a large physician outreach program which allowed for expansion of hospital services to community physicians and institutions. Ms. FitzGerald's specialties include medical staff relations, especially in regards to communication, negotiation, and facilitation, business development and sales, financial management and clinical support services, HIPAA, coding, and business analysis. She received a MHA from Suffolk University, Boston MA, a MS in Biotechnology and Management, a BS in Microbiology and a BS in Medical Technology from Salve Regina University. Ms. FitzGerald is also a Certified Professional Coder through the American Academy of Professional Coders. She is a member of various Laboratory and Management Associations. Ms. FitzGerald is also serving as a Lab Director at College of American Pathologist.",
            "hightlights": null,
            "headline": null,
            "phone": "+19784631096",
            "mobile": "508-843-9003",
            "phone2": null,
            "primaryPhoneType": "Cell",
            "alternatePhone": null,
            "smsDisabled": false,
            "countryName": "United States",
            "countryCode": "US",
            "companyId": 93761,
            "company": "ANNA JAQUES HOSPITAL",
            "title": "Director of Laboratory Services",
            "hasCurrentTerms": 1,
            "termsLastSigned": "2017-04-15T08:31:01.023Z",
            "termsExpiredDate": "2018-04-15T08:31:01.023Z",
            "language": "en",
            "isCouncilMember": true,
            "primaryPhone": "+19784631096",
            "pinNumber": 9155785,
            "conferenceNumber": {
                "didNumberId": "BC012291-424F-E711-8145-0E573F34979E",
                "displayNumber": "+19728517097",
                "countryCode": "US",
                "displayTitle": "United States",
                "provider": "twilio",
                "providerPhoneId": "PN1e399a9c223b5785ffe13f872f014274",
                "subProvider": null,
                "inboundPriority": 0,
                "outboundPriority": 0,
                "tollFree": false,
                "environment": "phadviger-devship",
                "providerPhoneLookup": "+19728517097",
                "activeInd": true,
                "outboundCountries": [],
                "priority": 0,
                "formattedNumber": "+1 972-851-7097",
                "autoDialNumber": "+19728517097,,9155785#"
            },
            "dialOutConferenceNumber": {
                "didNumberId": "BC012291-424F-E711-8145-0E573F34979E",
                "displayNumber": "+19728517097",
                "countryCode": "US",
                "displayTitle": "United States",
                "provider": "twilio",
                "providerPhoneId": "PN1e399a9c223b5785ffe13f872f014274",
                "subProvider": null,
                "inboundPriority": 0,
                "outboundPriority": 0,
                "tollFree": false,
                "environment": "phadviger-devship",
                "providerPhoneLookup": "+19728517097",
                "activeInd": true,
                "outboundCountries": [],
                "priority": 0,
                "formattedNumber": "+1 972-851-7097"
            }
        },
        "primaryContact": {
            "personId": 853782,
            "firstName": "Dima",
            "lastName": "Mostovoy",
            "title": "Analyst",
            "email": "dima.mostovoy@fmr.com",
            "preferredCulture": null,
            "contactId": 289005,
            "phone": "+1 617-563-1370",
            "mobile": "",
            "countryName": "United States",
            "countryCode": "US",
            "isClientContact": true,
            "allowCallReminder": true,
            "showClientMessaging": true,
            "pinNumber": 6568814,
            "conferenceNumber": {
                "didNumberId": "BC012291-424F-E711-8145-0E573F34979E",
                "displayNumber": "+19728517097",
                "countryCode": "US",
                "displayTitle": "United States",
                "provider": "twilio",
                "providerPhoneId": "PN1e399a9c223b5785ffe13f872f014274",
                "subProvider": null,
                "inboundPriority": 0,
                "outboundPriority": 0,
                "tollFree": false,
                "environment": "phadviger-devship",
                "providerPhoneLookup": "+19728517097",
                "activeInd": true,
                "outboundCountries": [],
                "priority": 0,
                "formattedNumber": "+1 972-851-7097",
                "autoDialNumber": "+19728517097,,6568814#"
            }
        },
        "assistant": {
            "firstName": "Emily",
            "lastName": "Lyons",
            "email": "emily.lyons@fmr.com"
        },
        "schedulingContact": {
            "personId": 853782,
            "firstName": "Dima",
            "lastName": "Mostovoy",
            "title": "Analyst",
            "email": "dima.mostovoy@fmr.com",
            "preferredCulture": null,
            "contactId": 289005,
            "phone": "+1 617-563-1370",
            "mobile": "",
            "countryName": "United States",
            "countryCode": "US",
            "isClientContact": true,
            "allowCallReminder": true,
            "showClientMessaging": true,
            "pinNumber": 6568814,
            "conferenceNumber": {
                "didNumberId": "BC012291-424F-E711-8145-0E573F34979E",
                "displayNumber": "+19728517097",
                "countryCode": "US",
                "displayTitle": "United States",
                "provider": "twilio",
                "providerPhoneId": "PN1e399a9c223b5785ffe13f872f014274",
                "subProvider": null,
                "inboundPriority": 0,
                "outboundPriority": 0,
                "tollFree": false,
                "environment": "phadviger-devship",
                "providerPhoneLookup": "+19728517097",
                "activeInd": true,
                "outboundCountries": [],
                "priority": 0,
                "formattedNumber": "+1 972-851-7097",
                "autoDialNumber": "+19728517097,,6568814#"
            }
        },
        "primaryManager": {
            "personId": 1065874,
            "firstName": "Eric",
            "lastName": "Dimise Ph.D.",
            "title": "Senior Research Manager",
            "email": "edimise@glgroup.com",
            "loginName": "glgroup\\edimise",
            "phone": "+1 617 603-2349",
            "isEmployee": true
        },
        "delegate": {
            "personId": 1120434,
            "firstName": "Bhumit",
            "lastName": "Shah",
            "title": "Senior Associate",
            "email": "bshah@glgroup.com",
            "isEmployee": true
        },
        "scheduler": {
            "personId": null,
            "firstName": null,
            "lastName": null,
            "title": null,
            "email": null,
            "phone": null,
            "isEmployee": true
        },
        "dialinIsInactive": true,
        "pinNumbers": [
            {
                "pinType": "client",
                "pinNumber": 6568814,
                "consultationParticipantId": 19303898,
                "active": true
            },
            {
                "pinType": "councilMember",
                "pinNumber": 9155785,
                "consultationParticipantId": 19303898,
                "active": true
            }
        ],
        "additionalDelegates": [
            {
                "id": 1015517,
                "firstname": "Karen",
                "lastname": "Wang",
                "email": "kwang2@glgroup.com",
                "consultationParticipantId": 19303898
            },
            {
                "id": 1050776,
                "firstname": "Betty",
                "lastname": "Gu",
                "email": "bgu@glgroup.com",
                "consultationParticipantId": 19303898
            }
        ],
        "msp": true,
        "defaultCallDuration": 60,
        "mspMarkup": false,
        "contractType": "CUSTOM OSP",
        "callLegs": [],
        "activeParticipantCount": 0,
        "billableTime": 0
    },
    {
        "consultationId": 2207093,
        "title": "Ortho Clinical Diagnostics' Clinical Lab Products",
        "titleLocalized": "Ortho Clinical Diagnostics的临床实验室产品",
        "titleLocalizedCulture": "zh",
        "consultationParticipantId": 19540851,
        "consultationParticipantStatusId": 2,
        "providerName": "twilio",
        "clientId": 85,
        "clientName": "Fidelity Investments",
        "callType": null,
        "scheduledDate": null,
        "lastUpdateDate": "2016-06-20T02:54:49.403Z",
        "status": null,
        "billableTimeRecorded": 0,
        "productTypeCategoryId": 1,
        "record": true,
        "transcribe": 0,
        "blockedByCompliance": false,
        "conferenceCallRequired": false,
        "auditorRequired": false,
        "client": {
            "id": 85,
            "name": "Fidelity Investments",
            "typeId": 2,
            "useGo": true,
            "isPSF": false
        },
        "blinding": {
            "hideClient": false,
            "hideCM": false,
            "councilMemberMaskingLabel": null
        },
        "councilMember": {
            "personId": 1471741,
            "firstName": "Ke",
            "lastName": "WANG",
            "email": "henney4@163.com",
            "preferredCulture": "zh-s",
            "councilMemberId": 1012453,
            "bio": "Ke WANG has been a Laboratory Technician Manager at Bengbu No.3 People's Hospital since Jul 2006. He is responsible for daily inspection; maintenance of the instrument; quality control; audit report and result explanation; related document preparation; training and coaching. He has been using the instruments like Johnson biochemical analyzer vitros250/350, 5600, 4600, hematology analyzer ABX M60, Mindray 5600/6800, sysmex2100E, Hitachi 7600, Chemclin 600, etc. He has solid experience in clinical lab products and has deep understanding towards the market dynamics.",
            "hightlights": null,
            "headline": null,
            "phone": null,
            "mobile": "+8615255278238",
            "phone2": null,
            "primaryPhoneType": null,
            "alternatePhone": null,
            "smsDisabled": true,
            "countryName": "China",
            "countryCode": "CN",
            "companyId": 3460633,
            "company": "Bengbu No.3 People's Hospital",
            "title": "Laboratory Technician Manager",
            "hasCurrentTerms": 1,
            "termsLastSigned": "2016-06-21T05:16:34.633Z",
            "termsExpiredDate": "2017-06-21T05:16:34.633Z",
            "language": "zh",
            "isCouncilMember": true,
            "primaryPhone": "+8615255278238",
            "pinNumber": 5056187,
            "conferenceNumber": {
                "didNumberId": "BC012291-424F-E711-8145-0E573F34979E",
                "displayNumber": "+19728517097",
                "countryCode": "US",
                "displayTitle": "United States",
                "provider": "twilio",
                "providerPhoneId": "PN1e399a9c223b5785ffe13f872f014274",
                "subProvider": null,
                "inboundPriority": 0,
                "outboundPriority": 0,
                "tollFree": false,
                "environment": "phadviger-devship",
                "providerPhoneLookup": "+19728517097",
                "activeInd": true,
                "outboundCountries": [],
                "priority": 0,
                "formattedNumber": "+1 972-851-7097",
                "autoDialNumber": "+19728517097,,5056187#"
            },
            "dialOutConferenceNumber": {
                "didNumberId": "BC012291-424F-E711-8145-0E573F34979E",
                "displayNumber": "+19728517097",
                "countryCode": "US",
                "displayTitle": "United States",
                "provider": "twilio",
                "providerPhoneId": "PN1e399a9c223b5785ffe13f872f014274",
                "subProvider": null,
                "inboundPriority": 0,
                "outboundPriority": 0,
                "tollFree": false,
                "environment": "phadviger-devship",
                "providerPhoneLookup": "+19728517097",
                "activeInd": true,
                "outboundCountries": [],
                "priority": 0,
                "formattedNumber": "+1 972-851-7097"
            }
        },
        "primaryContact": {
            "personId": 853782,
            "firstName": "Dima",
            "lastName": "Mostovoy",
            "title": "Analyst",
            "email": "dima.mostovoy@fmr.com",
            "preferredCulture": null,
            "contactId": 289005,
            "phone": "+1 617-563-1370",
            "mobile": "",
            "countryName": "United States",
            "countryCode": "US",
            "isClientContact": true,
            "allowCallReminder": true,
            "showClientMessaging": true,
            "pinNumber": 2679091,
            "conferenceNumber": {
                "didNumberId": "BC012291-424F-E711-8145-0E573F34979E",
                "displayNumber": "+19728517097",
                "countryCode": "US",
                "displayTitle": "United States",
                "provider": "twilio",
                "providerPhoneId": "PN1e399a9c223b5785ffe13f872f014274",
                "subProvider": null,
                "inboundPriority": 0,
                "outboundPriority": 0,
                "tollFree": false,
                "environment": "phadviger-devship",
                "providerPhoneLookup": "+19728517097",
                "activeInd": true,
                "outboundCountries": [],
                "priority": 0,
                "formattedNumber": "+1 972-851-7097",
                "autoDialNumber": "+19728517097,,2679091#"
            }
        },
        "assistant": {
            "firstName": "Emily",
            "lastName": "Lyons",
            "email": "emily.lyons@fmr.com"
        },
        "schedulingContact": {
            "personId": 853782,
            "firstName": "Dima",
            "lastName": "Mostovoy",
            "title": "Analyst",
            "email": "dima.mostovoy@fmr.com",
            "preferredCulture": null,
            "contactId": 289005,
            "phone": "+1 617-563-1370",
            "mobile": "",
            "countryName": "United States",
            "countryCode": "US",
            "isClientContact": true,
            "allowCallReminder": true,
            "showClientMessaging": true,
            "pinNumber": 2679091,
            "conferenceNumber": {
                "didNumberId": "BC012291-424F-E711-8145-0E573F34979E",
                "displayNumber": "+19728517097",
                "countryCode": "US",
                "displayTitle": "United States",
                "provider": "twilio",
                "providerPhoneId": "PN1e399a9c223b5785ffe13f872f014274",
                "subProvider": null,
                "inboundPriority": 0,
                "outboundPriority": 0,
                "tollFree": false,
                "environment": "phadviger-devship",
                "providerPhoneLookup": "+19728517097",
                "activeInd": true,
                "outboundCountries": [],
                "priority": 0,
                "formattedNumber": "+1 972-851-7097",
                "autoDialNumber": "+19728517097,,2679091#"
            }
        },
        "primaryManager": {
            "personId": 1065874,
            "firstName": "Eric",
            "lastName": "Dimise Ph.D.",
            "title": "Senior Research Manager",
            "email": "edimise@glgroup.com",
            "loginName": "glgroup\\edimise",
            "phone": "+1 617 603-2349",
            "isEmployee": true
        },
        "delegate": {
            "personId": 1120434,
            "firstName": "Bhumit",
            "lastName": "Shah",
            "title": "Senior Associate",
            "email": "bshah@glgroup.com",
            "isEmployee": true
        },
        "scheduler": {
            "personId": null,
            "firstName": null,
            "lastName": null,
            "title": null,
            "email": null,
            "phone": null,
            "isEmployee": true
        },
        "dialinIsInactive": true,
        "pinNumbers": [
            {
                "pinType": "councilMember",
                "pinNumber": 5056187,
                "consultationParticipantId": 19540851,
                "active": true
            },
            {
                "pinType": "client",
                "pinNumber": 2679091,
                "consultationParticipantId": 19540851,
                "active": true
            }
        ],
        "additionalDelegates": [
            {
                "id": 1015517,
                "firstname": "Karen",
                "lastname": "Wang",
                "email": "kwang2@glgroup.com",
                "consultationParticipantId": 19540851
            },
            {
                "id": 1050776,
                "firstname": "Betty",
                "lastname": "Gu",
                "email": "bgu@glgroup.com",
                "consultationParticipantId": 19540851
            }
        ],
        "msp": true,
        "defaultCallDuration": 60,
        "mspMarkup": false,
        "contractType": "CUSTOM OSP",
        "callLegs": [],
        "activeParticipantCount": 0,
        "billableTime": 0
    },
    {
        "consultationId": 2207093,
        "title": "Ortho Clinical Diagnostics' Clinical Lab Products",
        "titleLocalized": "Ortho Clinical Diagnostics的临床实验室产品",
        "titleLocalizedCulture": "zh",
        "consultationParticipantId": 19529940,
        "consultationParticipantStatusId": 2,
        "providerName": "twilio",
        "clientId": 85,
        "clientName": "Fidelity Investments",
        "callType": null,
        "scheduledDate": null,
        "lastUpdateDate": "2016-06-19T23:30:05.093Z",
        "status": null,
        "billableTimeRecorded": 0,
        "productTypeCategoryId": 1,
        "record": true,
        "transcribe": 0,
        "blockedByCompliance": false,
        "conferenceCallRequired": false,
        "auditorRequired": false,
        "client": {
            "id": 85,
            "name": "Fidelity Investments",
            "typeId": 2,
            "useGo": true,
            "isPSF": false
        },
        "blinding": {
            "hideClient": false,
            "hideCM": false,
            "councilMemberMaskingLabel": null
        },
        "councilMember": {
            "personId": 1470028,
            "firstName": "HongYan",
            "lastName": "JIA",
            "email": "jhyjhygg@163.com",
            "preferredCulture": null,
            "councilMemberId": 1010886,
            "bio": null,
            "hightlights": null,
            "headline": null,
            "phone": null,
            "mobile": "+8618661805601",
            "phone2": null,
            "primaryPhoneType": null,
            "alternatePhone": null,
            "smsDisabled": false,
            "countryName": "China",
            "countryCode": "CN",
            "companyId": 715551,
            "company": "Affiliated Hospital of Qingdao University Medical College",
            "title": "Leading Laboratory Physician",
            "hasCurrentTerms": 0,
            "termsLastSigned": null,
            "termsExpiredDate": null,
            "language": "en",
            "isCouncilMember": true,
            "primaryPhone": "+8618661805601",
            "pinNumber": 7077264,
            "conferenceNumber": {
                "didNumberId": "BC012291-424F-E711-8145-0E573F34979E",
                "displayNumber": "+19728517097",
                "countryCode": "US",
                "displayTitle": "United States",
                "provider": "twilio",
                "providerPhoneId": "PN1e399a9c223b5785ffe13f872f014274",
                "subProvider": null,
                "inboundPriority": 0,
                "outboundPriority": 0,
                "tollFree": false,
                "environment": "phadviger-devship",
                "providerPhoneLookup": "+19728517097",
                "activeInd": true,
                "outboundCountries": [],
                "priority": 0,
                "formattedNumber": "+1 972-851-7097",
                "autoDialNumber": "+19728517097,,7077264#"
            },
            "dialOutConferenceNumber": {
                "didNumberId": "BC012291-424F-E711-8145-0E573F34979E",
                "displayNumber": "+19728517097",
                "countryCode": "US",
                "displayTitle": "United States",
                "provider": "twilio",
                "providerPhoneId": "PN1e399a9c223b5785ffe13f872f014274",
                "subProvider": null,
                "inboundPriority": 0,
                "outboundPriority": 0,
                "tollFree": false,
                "environment": "phadviger-devship",
                "providerPhoneLookup": "+19728517097",
                "activeInd": true,
                "outboundCountries": [],
                "priority": 0,
                "formattedNumber": "+1 972-851-7097"
            }
        },
        "primaryContact": {
            "personId": 853782,
            "firstName": "Dima",
            "lastName": "Mostovoy",
            "title": "Analyst",
            "email": "dima.mostovoy@fmr.com",
            "preferredCulture": null,
            "contactId": 289005,
            "phone": "+1 617-563-1370",
            "mobile": "",
            "countryName": "United States",
            "countryCode": "US",
            "isClientContact": true,
            "allowCallReminder": true,
            "showClientMessaging": true,
            "pinNumber": 7794052,
            "conferenceNumber": {
                "didNumberId": "BC012291-424F-E711-8145-0E573F34979E",
                "displayNumber": "+19728517097",
                "countryCode": "US",
                "displayTitle": "United States",
                "provider": "twilio",
                "providerPhoneId": "PN1e399a9c223b5785ffe13f872f014274",
                "subProvider": null,
                "inboundPriority": 0,
                "outboundPriority": 0,
                "tollFree": false,
                "environment": "phadviger-devship",
                "providerPhoneLookup": "+19728517097",
                "activeInd": true,
                "outboundCountries": [],
                "priority": 0,
                "formattedNumber": "+1 972-851-7097",
                "autoDialNumber": "+19728517097,,7794052#"
            }
        },
        "assistant": {
            "firstName": "Emily",
            "lastName": "Lyons",
            "email": "emily.lyons@fmr.com"
        },
        "schedulingContact": {
            "personId": 853782,
            "firstName": "Dima",
            "lastName": "Mostovoy",
            "title": "Analyst",
            "email": "dima.mostovoy@fmr.com",
            "preferredCulture": null,
            "contactId": 289005,
            "phone": "+1 617-563-1370",
            "mobile": "",
            "countryName": "United States",
            "countryCode": "US",
            "isClientContact": true,
            "allowCallReminder": true,
            "showClientMessaging": true,
            "pinNumber": 7794052,
            "conferenceNumber": {
                "didNumberId": "BC012291-424F-E711-8145-0E573F34979E",
                "displayNumber": "+19728517097",
                "countryCode": "US",
                "displayTitle": "United States",
                "provider": "twilio",
                "providerPhoneId": "PN1e399a9c223b5785ffe13f872f014274",
                "subProvider": null,
                "inboundPriority": 0,
                "outboundPriority": 0,
                "tollFree": false,
                "environment": "phadviger-devship",
                "providerPhoneLookup": "+19728517097",
                "activeInd": true,
                "outboundCountries": [],
                "priority": 0,
                "formattedNumber": "+1 972-851-7097",
                "autoDialNumber": "+19728517097,,7794052#"
            }
        },
        "primaryManager": {
            "personId": 1065874,
            "firstName": "Eric",
            "lastName": "Dimise Ph.D.",
            "title": "Senior Research Manager",
            "email": "edimise@glgroup.com",
            "loginName": "glgroup\\edimise",
            "phone": "+1 617 603-2349",
            "isEmployee": true
        },
        "delegate": {
            "personId": 1120434,
            "firstName": "Bhumit",
            "lastName": "Shah",
            "title": "Senior Associate",
            "email": "bshah@glgroup.com",
            "isEmployee": true
        },
        "scheduler": {
            "personId": null,
            "firstName": null,
            "lastName": null,
            "title": null,
            "email": null,
            "phone": null,
            "isEmployee": true
        },
        "dialinIsInactive": true,
        "pinNumbers": [
            {
                "pinType": "councilMember",
                "pinNumber": 7077264,
                "consultationParticipantId": 19529940,
                "active": true
            },
            {
                "pinType": "client",
                "pinNumber": 7794052,
                "consultationParticipantId": 19529940,
                "active": true
            }
        ],
        "additionalDelegates": [
            {
                "id": 1015517,
                "firstname": "Karen",
                "lastname": "Wang",
                "email": "kwang2@glgroup.com",
                "consultationParticipantId": 19529940
            },
            {
                "id": 1050776,
                "firstname": "Betty",
                "lastname": "Gu",
                "email": "bgu@glgroup.com",
                "consultationParticipantId": 19529940
            }
        ],
        "msp": true,
        "defaultCallDuration": 60,
        "mspMarkup": false,
        "contractType": "CUSTOM OSP",
        "callLegs": [],
        "activeParticipantCount": 0,
        "billableTime": 0
    },
    {
        "consultationId": 2207093,
        "title": "Ortho Clinical Diagnostics' Clinical Lab Products",
        "titleLocalized": "Ortho Clinical Diagnostics的临床实验室产品",
        "titleLocalizedCulture": "zh",
        "consultationParticipantId": 19303904,
        "consultationParticipantStatusId": 5,
        "providerName": "twilio",
        "clientId": 85,
        "clientName": "Fidelity Investments",
        "callType": null,
        "scheduledDate": null,
        "lastUpdateDate": "2016-06-18T19:52:29.050Z",
        "status": null,
        "billableTimeRecorded": 0,
        "productTypeCategoryId": 1,
        "record": true,
        "transcribe": 0,
        "blockedByCompliance": false,
        "conferenceCallRequired": false,
        "auditorRequired": false,
        "client": {
            "id": 85,
            "name": "Fidelity Investments",
            "typeId": 2,
            "useGo": true,
            "isPSF": false
        },
        "blinding": {
            "hideClient": false,
            "hideCM": false,
            "councilMemberMaskingLabel": null
        },
        "councilMember": {
            "personId": 684775,
            "firstName": "Bryan",
            "lastName": "Hunter",
            "email": "bfitz1373@yahoo.com",
            "preferredCulture": "en",
            "councilMemberId": 476120,
            "bio": "Bryan Hunter is a Lab Manager at the renowned UCSF Medical Center, San Francisco CA. Previously, he was the Clinical Laboratory Director at Shriners Hospital, from 2007 to 2013.",
            "hightlights": null,
            "headline": null,
            "phone": "650-696-5510",
            "mobile": null,
            "phone2": null,
            "primaryPhoneType": "office",
            "alternatePhone": null,
            "smsDisabled": false,
            "countryName": "United States",
            "countryCode": "US",
            "companyId": 719153,
            "company": "UCSF Children's Hospital",
            "title": "Lab Manager",
            "hasCurrentTerms": 0,
            "termsLastSigned": "2015-11-26T19:29:24.590Z",
            "termsExpiredDate": "2016-11-25T19:29:24.590Z",
            "language": "en",
            "isCouncilMember": true,
            "primaryPhone": "650-696-5510",
            "pinNumber": 5443264,
            "conferenceNumber": {
                "didNumberId": "BC012291-424F-E711-8145-0E573F34979E",
                "displayNumber": "+19728517097",
                "countryCode": "US",
                "displayTitle": "United States",
                "provider": "twilio",
                "providerPhoneId": "PN1e399a9c223b5785ffe13f872f014274",
                "subProvider": null,
                "inboundPriority": 0,
                "outboundPriority": 0,
                "tollFree": false,
                "environment": "phadviger-devship",
                "providerPhoneLookup": "+19728517097",
                "activeInd": true,
                "outboundCountries": [],
                "priority": 0,
                "formattedNumber": "+1 972-851-7097",
                "autoDialNumber": "+19728517097,,5443264#"
            },
            "dialOutConferenceNumber": {
                "didNumberId": "BC012291-424F-E711-8145-0E573F34979E",
                "displayNumber": "+19728517097",
                "countryCode": "US",
                "displayTitle": "United States",
                "provider": "twilio",
                "providerPhoneId": "PN1e399a9c223b5785ffe13f872f014274",
                "subProvider": null,
                "inboundPriority": 0,
                "outboundPriority": 0,
                "tollFree": false,
                "environment": "phadviger-devship",
                "providerPhoneLookup": "+19728517097",
                "activeInd": true,
                "outboundCountries": [],
                "priority": 0,
                "formattedNumber": "+1 972-851-7097"
            }
        },
        "primaryContact": {
            "personId": 853782,
            "firstName": "Dima",
            "lastName": "Mostovoy",
            "title": "Analyst",
            "email": "dima.mostovoy@fmr.com",
            "preferredCulture": null,
            "contactId": 289005,
            "phone": "+1 617-563-1370",
            "mobile": "",
            "countryName": "United States",
            "countryCode": "US",
            "isClientContact": true,
            "allowCallReminder": true,
            "showClientMessaging": true,
            "pinNumber": 4808338,
            "conferenceNumber": {
                "didNumberId": "BC012291-424F-E711-8145-0E573F34979E",
                "displayNumber": "+19728517097",
                "countryCode": "US",
                "displayTitle": "United States",
                "provider": "twilio",
                "providerPhoneId": "PN1e399a9c223b5785ffe13f872f014274",
                "subProvider": null,
                "inboundPriority": 0,
                "outboundPriority": 0,
                "tollFree": false,
                "environment": "phadviger-devship",
                "providerPhoneLookup": "+19728517097",
                "activeInd": true,
                "outboundCountries": [],
                "priority": 0,
                "formattedNumber": "+1 972-851-7097",
                "autoDialNumber": "+19728517097,,4808338#"
            }
        },
        "assistant": {
            "firstName": "Emily",
            "lastName": "Lyons",
            "email": "emily.lyons@fmr.com"
        },
        "schedulingContact": {
            "personId": 853782,
            "firstName": "Dima",
            "lastName": "Mostovoy",
            "title": "Analyst",
            "email": "dima.mostovoy@fmr.com",
            "preferredCulture": null,
            "contactId": 289005,
            "phone": "+1 617-563-1370",
            "mobile": "",
            "countryName": "United States",
            "countryCode": "US",
            "isClientContact": true,
            "allowCallReminder": true,
            "showClientMessaging": true,
            "pinNumber": 4808338,
            "conferenceNumber": {
                "didNumberId": "BC012291-424F-E711-8145-0E573F34979E",
                "displayNumber": "+19728517097",
                "countryCode": "US",
                "displayTitle": "United States",
                "provider": "twilio",
                "providerPhoneId": "PN1e399a9c223b5785ffe13f872f014274",
                "subProvider": null,
                "inboundPriority": 0,
                "outboundPriority": 0,
                "tollFree": false,
                "environment": "phadviger-devship",
                "providerPhoneLookup": "+19728517097",
                "activeInd": true,
                "outboundCountries": [],
                "priority": 0,
                "formattedNumber": "+1 972-851-7097",
                "autoDialNumber": "+19728517097,,4808338#"
            }
        },
        "primaryManager": {
            "personId": 1065874,
            "firstName": "Eric",
            "lastName": "Dimise Ph.D.",
            "title": "Senior Research Manager",
            "email": "edimise@glgroup.com",
            "loginName": "glgroup\\edimise",
            "phone": "+1 617 603-2349",
            "isEmployee": true
        },
        "delegate": {
            "personId": 1120434,
            "firstName": "Bhumit",
            "lastName": "Shah",
            "title": "Senior Associate",
            "email": "bshah@glgroup.com",
            "isEmployee": true
        },
        "scheduler": {
            "personId": null,
            "firstName": null,
            "lastName": null,
            "title": null,
            "email": null,
            "phone": null,
            "isEmployee": true
        },
        "dialinIsInactive": true,
        "pinNumbers": [
            {
                "pinType": "client",
                "pinNumber": 4808338,
                "consultationParticipantId": 19303904,
                "active": true
            },
            {
                "pinType": "councilMember",
                "pinNumber": 5443264,
                "consultationParticipantId": 19303904,
                "active": true
            }
        ],
        "additionalDelegates": [
            {
                "id": 1015517,
                "firstname": "Karen",
                "lastname": "Wang",
                "email": "kwang2@glgroup.com",
                "consultationParticipantId": 19303904
            },
            {
                "id": 1050776,
                "firstname": "Betty",
                "lastname": "Gu",
                "email": "bgu@glgroup.com",
                "consultationParticipantId": 19303904
            }
        ],
        "msp": true,
        "defaultCallDuration": 60,
        "mspMarkup": false,
        "contractType": "CUSTOM OSP",
        "callLegs": [],
        "activeParticipantCount": 0,
        "billableTime": 0
    },
    {
        "consultationId": 2207093,
        "title": "Ortho Clinical Diagnostics' Clinical Lab Products",
        "titleLocalized": "Ortho Clinical Diagnostics的临床实验室产品",
        "titleLocalizedCulture": "zh",
        "consultationParticipantId": 19355804,
        "consultationParticipantStatusId": 4,
        "providerName": "twilio",
        "clientId": 85,
        "clientName": "Fidelity Investments",
        "callType": null,
        "scheduledDate": null,
        "lastUpdateDate": "2016-06-06T01:04:28.186Z",
        "status": null,
        "billableTimeRecorded": 0,
        "productTypeCategoryId": 1,
        "record": true,
        "transcribe": 0,
        "blockedByCompliance": false,
        "conferenceCallRequired": false,
        "auditorRequired": false,
        "client": {
            "id": 85,
            "name": "Fidelity Investments",
            "typeId": 2,
            "useGo": true,
            "isPSF": false
        },
        "blinding": {
            "hideClient": false,
            "hideCM": false,
            "councilMemberMaskingLabel": null
        },
        "councilMember": {
            "personId": 752507,
            "firstName": "Bo",
            "lastName": "ZHANG",
            "email": "zhangbocq@aliyun.com",
            "preferredCulture": "zh-s",
            "councilMemberId": 509619,
            "bio": "Bo ZHANG is a Chief Physician, Professor and the Deputy Department Head at the Laboratory Department of Southwest Hospital, Chongqing, where he has worked since July 1991. Southwest Hospital is a 3A hospital in Chongqing, China. Dr. Zhang specializes in clinical biochemistry, immunology, microbiology and molecular diagnostics in China.",
            "hightlights": null,
            "headline": null,
            "phone": "+8618716427659",
            "mobile": null,
            "phone2": "+86 23-68765446",
            "primaryPhoneType": "Office",
            "alternatePhone": null,
            "smsDisabled": false,
            "countryName": "China",
            "countryCode": "CN",
            "companyId": 1234034,
            "company": "Southwest Hospital",
            "title": "Chief Physician, Professor and Deputy Head",
            "hasCurrentTerms": 1,
            "termsLastSigned": "2017-02-02T08:55:47.800Z",
            "termsExpiredDate": "2018-02-02T08:55:47.800Z",
            "language": "zh",
            "isCouncilMember": true,
            "primaryPhone": "+8618716427659",
            "pinNumber": 3092970,
            "conferenceNumber": {
                "didNumberId": "BC012291-424F-E711-8145-0E573F34979E",
                "displayNumber": "+19728517097",
                "countryCode": "US",
                "displayTitle": "United States",
                "provider": "twilio",
                "providerPhoneId": "PN1e399a9c223b5785ffe13f872f014274",
                "subProvider": null,
                "inboundPriority": 0,
                "outboundPriority": 0,
                "tollFree": false,
                "environment": "phadviger-devship",
                "providerPhoneLookup": "+19728517097",
                "activeInd": true,
                "outboundCountries": [],
                "priority": 0,
                "formattedNumber": "+1 972-851-7097",
                "autoDialNumber": "+19728517097,,3092970#"
            },
            "dialOutConferenceNumber": {
                "didNumberId": "BC012291-424F-E711-8145-0E573F34979E",
                "displayNumber": "+19728517097",
                "countryCode": "US",
                "displayTitle": "United States",
                "provider": "twilio",
                "providerPhoneId": "PN1e399a9c223b5785ffe13f872f014274",
                "subProvider": null,
                "inboundPriority": 0,
                "outboundPriority": 0,
                "tollFree": false,
                "environment": "phadviger-devship",
                "providerPhoneLookup": "+19728517097",
                "activeInd": true,
                "outboundCountries": [],
                "priority": 0,
                "formattedNumber": "+1 972-851-7097"
            }
        },
        "primaryContact": {
            "personId": 853782,
            "firstName": "Dima",
            "lastName": "Mostovoy",
            "title": "Analyst",
            "email": "dima.mostovoy@fmr.com",
            "preferredCulture": null,
            "contactId": 289005,
            "phone": "+1 617-563-1370",
            "mobile": "",
            "countryName": "United States",
            "countryCode": "US",
            "isClientContact": true,
            "allowCallReminder": true,
            "showClientMessaging": true,
            "pinNumber": 2352491,
            "conferenceNumber": {
                "didNumberId": "BC012291-424F-E711-8145-0E573F34979E",
                "displayNumber": "+19728517097",
                "countryCode": "US",
                "displayTitle": "United States",
                "provider": "twilio",
                "providerPhoneId": "PN1e399a9c223b5785ffe13f872f014274",
                "subProvider": null,
                "inboundPriority": 0,
                "outboundPriority": 0,
                "tollFree": false,
                "environment": "phadviger-devship",
                "providerPhoneLookup": "+19728517097",
                "activeInd": true,
                "outboundCountries": [],
                "priority": 0,
                "formattedNumber": "+1 972-851-7097",
                "autoDialNumber": "+19728517097,,2352491#"
            }
        },
        "assistant": {
            "firstName": "Emily",
            "lastName": "Lyons",
            "email": "emily.lyons@fmr.com"
        },
        "schedulingContact": {
            "personId": 853782,
            "firstName": "Dima",
            "lastName": "Mostovoy",
            "title": "Analyst",
            "email": "dima.mostovoy@fmr.com",
            "preferredCulture": null,
            "contactId": 289005,
            "phone": "+1 617-563-1370",
            "mobile": "",
            "countryName": "United States",
            "countryCode": "US",
            "isClientContact": true,
            "allowCallReminder": true,
            "showClientMessaging": true,
            "pinNumber": 2352491,
            "conferenceNumber": {
                "didNumberId": "BC012291-424F-E711-8145-0E573F34979E",
                "displayNumber": "+19728517097",
                "countryCode": "US",
                "displayTitle": "United States",
                "provider": "twilio",
                "providerPhoneId": "PN1e399a9c223b5785ffe13f872f014274",
                "subProvider": null,
                "inboundPriority": 0,
                "outboundPriority": 0,
                "tollFree": false,
                "environment": "phadviger-devship",
                "providerPhoneLookup": "+19728517097",
                "activeInd": true,
                "outboundCountries": [],
                "priority": 0,
                "formattedNumber": "+1 972-851-7097",
                "autoDialNumber": "+19728517097,,2352491#"
            }
        },
        "primaryManager": {
            "personId": 1065874,
            "firstName": "Eric",
            "lastName": "Dimise Ph.D.",
            "title": "Senior Research Manager",
            "email": "edimise@glgroup.com",
            "loginName": "glgroup\\edimise",
            "phone": "+1 617 603-2349",
            "isEmployee": true
        },
        "delegate": {
            "personId": 1120434,
            "firstName": "Bhumit",
            "lastName": "Shah",
            "title": "Senior Associate",
            "email": "bshah@glgroup.com",
            "isEmployee": true
        },
        "scheduler": {
            "personId": null,
            "firstName": null,
            "lastName": null,
            "title": null,
            "email": null,
            "phone": null,
            "isEmployee": true
        },
        "dialinIsInactive": true,
        "pinNumbers": [
            {
                "pinType": "client",
                "pinNumber": 2352491,
                "consultationParticipantId": 19355804,
                "active": true
            },
            {
                "pinType": "councilMember",
                "pinNumber": 3092970,
                "consultationParticipantId": 19355804,
                "active": true
            }
        ],
        "additionalDelegates": [
            {
                "id": 1015517,
                "firstname": "Karen",
                "lastname": "Wang",
                "email": "kwang2@glgroup.com",
                "consultationParticipantId": 19355804
            },
            {
                "id": 1050776,
                "firstname": "Betty",
                "lastname": "Gu",
                "email": "bgu@glgroup.com",
                "consultationParticipantId": 19355804
            }
        ],
        "msp": true,
        "defaultCallDuration": 60,
        "mspMarkup": false,
        "contractType": "CUSTOM OSP",
        "callLegs": [],
        "activeParticipantCount": 0,
        "billableTime": 0
    },
    {
        "consultationId": 2207093,
        "title": "Ortho Clinical Diagnostics' Clinical Lab Products",
        "titleLocalized": "Ortho Clinical Diagnostics的临床实验室产品",
        "titleLocalizedCulture": "zh",
        "consultationParticipantId": 19355797,
        "consultationParticipantStatusId": 3,
        "providerName": "twilio",
        "clientId": 85,
        "clientName": "Fidelity Investments",
        "callType": null,
        "scheduledDate": null,
        "lastUpdateDate": "2016-06-01T22:01:04.626Z",
        "status": null,
        "billableTimeRecorded": 0,
        "productTypeCategoryId": 1,
        "record": true,
        "transcribe": 0,
        "blockedByCompliance": false,
        "conferenceCallRequired": false,
        "auditorRequired": false,
        "client": {
            "id": 85,
            "name": "Fidelity Investments",
            "typeId": 2,
            "useGo": true,
            "isPSF": false
        },
        "blinding": {
            "hideClient": false,
            "hideCM": false,
            "councilMemberMaskingLabel": null
        },
        "councilMember": {
            "personId": 899399,
            "firstName": "Jian",
            "lastName": "TONG",
            "email": "371913822@qq.com",
            "preferredCulture": "zh-s",
            "councilMemberId": 582713,
            "bio": "Mr. Jian TONG is Deputy Chief Physician at Clinical Lab Department of Chaoyang Lai Guang Ying Hospital (ClassI, Beijing, T1) where he has worked since January 2006. Mr. Tong was Physician in Beijing Hospital(ClassIIIA, Beijing, T1)and is familiar with clinical lab technologies. Mr. Tong has 15 year clinical lab working experience and has knowledge on clinical management and equipment purchase process. Other work experience: Since 2010, it is involved in the formation of hospital hygiene station information system [the hospital outpatient denominated charges + outpatient pharmacy dispensing + outpatient pharmacies Management + the storeroom Management + admission and discharge management + nurses work management + electronic medical records system + Chinese doctor's orders]. In other sections of the hospital I work, such as pharmacy, storeroom and Devices Division, Medicare, do, radiology, clinical departments also have part-time jobs., and have Get a psychological counseling nationally recognized qualification.",
            "hightlights": null,
            "headline": null,
            "phone": "+86 138 1072 0789",
            "mobile": "+86 138 1072 0789",
            "phone2": null,
            "primaryPhoneType": null,
            "alternatePhone": null,
            "smsDisabled": false,
            "countryName": "China",
            "countryCode": "CN",
            "companyId": 2107839,
            "company": "Lai Guang Ying Hospital",
            "title": "Deputy Chief Physician",
            "hasCurrentTerms": 0,
            "termsLastSigned": "2015-03-16T07:12:46.683Z",
            "termsExpiredDate": "2016-03-15T07:12:46.683Z",
            "language": "zh",
            "isCouncilMember": true,
            "primaryPhone": "+86 138 1072 0789",
            "pinNumber": 3975944,
            "conferenceNumber": {
                "didNumberId": "BC012291-424F-E711-8145-0E573F34979E",
                "displayNumber": "+19728517097",
                "countryCode": "US",
                "displayTitle": "United States",
                "provider": "twilio",
                "providerPhoneId": "PN1e399a9c223b5785ffe13f872f014274",
                "subProvider": null,
                "inboundPriority": 0,
                "outboundPriority": 0,
                "tollFree": false,
                "environment": "phadviger-devship",
                "providerPhoneLookup": "+19728517097",
                "activeInd": true,
                "outboundCountries": [],
                "priority": 0,
                "formattedNumber": "+1 972-851-7097",
                "autoDialNumber": "+19728517097,,3975944#"
            },
            "dialOutConferenceNumber": {
                "didNumberId": "BC012291-424F-E711-8145-0E573F34979E",
                "displayNumber": "+19728517097",
                "countryCode": "US",
                "displayTitle": "United States",
                "provider": "twilio",
                "providerPhoneId": "PN1e399a9c223b5785ffe13f872f014274",
                "subProvider": null,
                "inboundPriority": 0,
                "outboundPriority": 0,
                "tollFree": false,
                "environment": "phadviger-devship",
                "providerPhoneLookup": "+19728517097",
                "activeInd": true,
                "outboundCountries": [],
                "priority": 0,
                "formattedNumber": "+1 972-851-7097"
            }
        },
        "primaryContact": {
            "personId": 853782,
            "firstName": "Dima",
            "lastName": "Mostovoy",
            "title": "Analyst",
            "email": "dima.mostovoy@fmr.com",
            "preferredCulture": null,
            "contactId": 289005,
            "phone": "+1 617-563-1370",
            "mobile": "",
            "countryName": "United States",
            "countryCode": "US",
            "isClientContact": true,
            "allowCallReminder": true,
            "showClientMessaging": true,
            "pinNumber": 8476615,
            "conferenceNumber": {
                "didNumberId": "BC012291-424F-E711-8145-0E573F34979E",
                "displayNumber": "+19728517097",
                "countryCode": "US",
                "displayTitle": "United States",
                "provider": "twilio",
                "providerPhoneId": "PN1e399a9c223b5785ffe13f872f014274",
                "subProvider": null,
                "inboundPriority": 0,
                "outboundPriority": 0,
                "tollFree": false,
                "environment": "phadviger-devship",
                "providerPhoneLookup": "+19728517097",
                "activeInd": true,
                "outboundCountries": [],
                "priority": 0,
                "formattedNumber": "+1 972-851-7097",
                "autoDialNumber": "+19728517097,,8476615#"
            }
        },
        "assistant": {
            "firstName": "Emily",
            "lastName": "Lyons",
            "email": "emily.lyons@fmr.com"
        },
        "schedulingContact": {
            "personId": 853782,
            "firstName": "Dima",
            "lastName": "Mostovoy",
            "title": "Analyst",
            "email": "dima.mostovoy@fmr.com",
            "preferredCulture": null,
            "contactId": 289005,
            "phone": "+1 617-563-1370",
            "mobile": "",
            "countryName": "United States",
            "countryCode": "US",
            "isClientContact": true,
            "allowCallReminder": true,
            "showClientMessaging": true,
            "pinNumber": 8476615,
            "conferenceNumber": {
                "didNumberId": "BC012291-424F-E711-8145-0E573F34979E",
                "displayNumber": "+19728517097",
                "countryCode": "US",
                "displayTitle": "United States",
                "provider": "twilio",
                "providerPhoneId": "PN1e399a9c223b5785ffe13f872f014274",
                "subProvider": null,
                "inboundPriority": 0,
                "outboundPriority": 0,
                "tollFree": false,
                "environment": "phadviger-devship",
                "providerPhoneLookup": "+19728517097",
                "activeInd": true,
                "outboundCountries": [],
                "priority": 0,
                "formattedNumber": "+1 972-851-7097",
                "autoDialNumber": "+19728517097,,8476615#"
            }
        },
        "primaryManager": {
            "personId": 1065874,
            "firstName": "Eric",
            "lastName": "Dimise Ph.D.",
            "title": "Senior Research Manager",
            "email": "edimise@glgroup.com",
            "loginName": "glgroup\\edimise",
            "phone": "+1 617 603-2349",
            "isEmployee": true
        },
        "delegate": {
            "personId": 1120434,
            "firstName": "Bhumit",
            "lastName": "Shah",
            "title": "Senior Associate",
            "email": "bshah@glgroup.com",
            "isEmployee": true
        },
        "scheduler": {
            "personId": null,
            "firstName": null,
            "lastName": null,
            "title": null,
            "email": null,
            "phone": null,
            "isEmployee": true
        },
        "dialinIsInactive": true,
        "pinNumbers": [
            {
                "pinType": "councilMember",
                "pinNumber": 3975944,
                "consultationParticipantId": 19355797,
                "active": true
            },
            {
                "pinType": "client",
                "pinNumber": 8476615,
                "consultationParticipantId": 19355797,
                "active": true
            }
        ],
        "additionalDelegates": [
            {
                "id": 1015517,
                "firstname": "Karen",
                "lastname": "Wang",
                "email": "kwang2@glgroup.com",
                "consultationParticipantId": 19355797
            },
            {
                "id": 1050776,
                "firstname": "Betty",
                "lastname": "Gu",
                "email": "bgu@glgroup.com",
                "consultationParticipantId": 19355797
            }
        ],
        "msp": true,
        "defaultCallDuration": 60,
        "mspMarkup": false,
        "contractType": "CUSTOM OSP",
        "callLegs": [],
        "activeParticipantCount": 0,
        "billableTime": 0
    }
]